shruggingface/__init__.py
shruggingface/__main__.py
shruggingface/cli.py
shruggingface/env.py
shruggingface/pack.py
shruggingface/pull.py
shruggingface/push.py
shruggingface-0.1.0.dist-info/METADATA
shruggingface-0.1.0.dist-info/WHEEL
shruggingface-0.1.0.dist-info/entry_points.txt
shruggingface-0.1.0.dist-info/RECORD
