Metadata-Version: 2.1
Name: shruggingface
Version: 0.1.0
Summary: back up and restore huggingface models
License: Public Domain
Author: Gareth Davidson
Author-email: gaz@bitplane.net
Requires-Python: >=3.9,<4.0
Classifier: License :: Other/Proprietary License
Classifier: Programming Language :: Python :: 3
Classifier: Programming Language :: Python :: 3.9
Classifier: Programming Language :: Python :: 3.10
Classifier: Programming Language :: Python :: 3.11
Classifier: Programming Language :: Python :: 3.12
Classifier: Programming Language :: Python :: 3.13
Requires-Dist: click (>=8.1,<9.0)
